{
  "numLevels": 1,
  "props": {
    "player": {
      "acceleration": 0.12,
      "maxRotVelocity": 10,
      "maxVelocity": 2,
      "rotAcceleration": 2,
      "weapons": {
        "pistol": {
          "equiped": true,
          "idleTime": 20,
          "power": 3,
          "maxAmmo": 100,
          "recoil": 4,
          "range": 1
        },
        "shotgun": {
          "equiped": false,
          "idleTime": 300,
          "power": 15,
          "maxAmmo": 60,
          "recoil": 15,
          "range": 2
        },
        "chaingun": {
          "equiped": false,
          "idleTime": 0,
          "power": 4,
          "maxAmmo": 200,
          "recoil": 5,
          "range": 1
        }
      },
      "camera": {
        "heightIncrement": 0.04,
        "maxHeight": 1,
        "pitchVelocity": 4,
        "maxRecoilAmount": 12,
        "minRecoilAmount": 1,
        "recoilFade": 0.2,
        "maxShakeAmount": 10,
        "minShakeAmount": 1,
        "shakeFade": 0.65,
        "maxPitch": 196
      }
    },
    "enemies": {
      "grunt": {
        "acceleration": 0.2,
        "maxVelocity": 1,
        "attackRange": 160,
        "attackTime": 500,
        "alertTime": 500,
        "aimTime": 400,
        "hurtTime": 400,
        "maxHealth": 5,
        "attackPower": 5,
        "clipSize": 3
      }
    },
    "door": {
      "speed": 2,
      "interval": 2000
    },
    "world": {
      "brightness": -0.25,
      "visibility": 1000
    }
  }
}
